sql_schema_registry/__init__.py
sql_schema_registry/database.py
sql_schema_registry/files.py
sql_schema_registry-0.2.7.dist-info/METADATA
sql_schema_registry-0.2.7.dist-info/WHEEL
sql_schema_registry-0.2.7.dist-info/top_level.txt
sql_schema_registry-0.2.7.dist-info/RECORD
