Metadata-Version: 2.1
Name: sql-schema-registry
Version: 0.2.7
Summary: Schema registry
Author: Alejandro Liz
License: MIT
